elib_config/__init__.py
elib_config/_exc.py
elib_config/_logging.py
elib_config/_setup.py
elib_config/_types.py
elib_config/_utils.py
elib_config/_validate.py
elib_config/_file/__init__.py
elib_config/_file/_config_example.py
elib_config/_file/_config_example_header.py
elib_config/_file/_config_file.py
elib_config/_file/_exc.py
elib_config/_value/__init__.py
elib_config/_value/_config_value.py
elib_config/_value/_config_value_bool.py
elib_config/_value/_config_value_float.py
elib_config/_value/_config_value_integer.py
elib_config/_value/_config_value_list.py
elib_config/_value/_config_value_path.py
elib_config/_value/_config_value_string.py
elib_config/_value/_config_value_table.py
elib_config/_value/_config_value_toml.py
elib_config/_value/_exc.py
test/__init__.py
test/conftest.py
test/test_config_file.py
test/test_config_value.py
test/test_config_value_bool.py
test/test_config_value_float.py
test/test_config_value_integer.py
test/test_config_value_list.py
test/test_config_value_path.py
test/test_config_value_root_path.py
test/test_config_value_string.py
test/test_config_value_table.py
test/test_error_string.py
test/test_example_config.py
test/test_setup.py
test/test_utils.py
test/test_validate.py
elib_config-2018.12.18.1.dist-info/LICENSE
elib_config-2018.12.18.1.dist-info/METADATA
elib_config-2018.12.18.1.dist-info/WHEEL
elib_config-2018.12.18.1.dist-info/entry_points.txt
elib_config-2018.12.18.1.dist-info/top_level.txt
elib_config-2018.12.18.1.dist-info/RECORD
