Metadata-Version: 2.1
Name: elib-config
Version: 2018.12.18.1
Summary: My own poor little attempt at a config lib
Home-page: https://github.com/etcher-be/elib_config
Author: etcher-be
Author-email: elib_config@daribouca.net
License: MIT
Download-URL: https://github.com/etcher-be/elib_config/releases
Platform: win32
Classifier: Development Status :: 3 - Alpha
Classifier: Topic :: Utilities
Classifier: License :: OSI Approved :: MIT License
Classifier: Environment :: Win32 (MS Windows)
Classifier: Intended Audience :: Developers
Classifier: Natural Language :: English
Classifier: Operating System :: OS Independent
Classifier: Topic :: Software Development :: Libraries :: Python Modules
Classifier: Programming Language :: Cython
Classifier: Programming Language :: Python
Classifier: Programming Language :: Python :: 3 :: Only
Classifier: Programming Language :: Python :: 3.6
Classifier: Programming Language :: Python :: Implementation
Classifier: Programming Language :: Python :: Implementation :: CPython
Classifier: Topic :: Utilities
Requires-Python: >=3.6
Requires-Dist: tomlkit
Requires-Dist: setuptools-scm
